{
	"imports":
	[
		{
			"file": "native-common.json"
		}
	],
	"variables":
	[
		{
			"name": "STEAMAPPS",
			"value": "%HOME%/.local/share/wineprefixes/Steam/drive_c/Program Files/Steam/steamapps/common"
		},
		{
			"name": "WINEPREFIX_ROOT",
			"value": "%HOME%/.local/share/wineprefixes"
		},
		{
			"name": "TOOLS",
			"value": "%HOME%/.local/share/winescripts/tools"
		},
		{
			"name": "WINEBUILDS",
			"value": "%HOME%/.local/share/wineversions"
		}
	],
	"subsystems":
	[
		{
			"type": "constant",
			"environment":
			[
				{
					"name": "PULSE_LATENCY_MSEC",
					"value": "60"
				}
			]
		}
		
	],
	"wine.postrun":
	[
		{
			"title": "Setting gamma",
			"sys.exec": "xgamma -gamma 1.0"
		}
	],
	"systems":
	[
		{
			"type": "launcher",
			"config-prefix": "wine",
			"launch-prefix": "wine",
			"": "",
			"variables":
			[
				{
					"type": "config-input",
					"name": "WINEVERSION",
					"input": "version"
				},
				{
					"type": "config-input",
					"name": "WINEPREFIX_ID",
					"input": "wineprefix-id"
				}
			],
			"environment":
			[
				{
					"name": "PATH",
					"value": "%PATH%:%WINEBUILDS%/%WINEVERSION%/bin"
				},
				{
					"name": "LD_LIBRARY_PATH",
					"value": "%LD_LIBRARY_PATH%:%WINEBUILDS%/%WINEVERSION%/lib:%WINEBUILDS%/lib64"
				},
				{
					"name": "XDG_DATA_DIRS",
					"value": "%XDG_DATA_DIRS%:%WINEBUILDS%/%WINEVERSION%/share"
				},
				{
					"name": "WINEPREFIX",
					"value": "%WINEPREFIX_ROOT%/%WINEPREFIX_ID%"
				}
			]
		},
		{
			"type": "launcher",
			"config-prefix": "sys",
			"launch-prefix": "",
			"actions":
			[
				{
					"type": "prelaunch"
				}
			]
		}
	]
}
